msprobe/CMakeLists.txt
msprobe/README.md
msprobe/__init__.py
msprobe/config.json
msprobe/msprobe.py
msprobe/core/__init__.py
msprobe/core/common_config.py
msprobe/core/hook_manager.py
msprobe/core/service.py
msprobe/core/advisor/advisor.py
msprobe/core/advisor/advisor_const.py
msprobe/core/advisor/advisor_result.py
msprobe/core/common/const.py
msprobe/core/common/db_manager.py
msprobe/core/common/decorator.py
msprobe/core/common/exceptions.py
msprobe/core/common/file_utils.py
msprobe/core/common/framework_adapter.py
msprobe/core/common/global_lock.py
msprobe/core/common/inplace_op_checker.py
msprobe/core/common/inplace_ops.yaml
msprobe/core/common/log.py
msprobe/core/common/megatron_utils.py
msprobe/core/common/parallel_state.py
msprobe/core/common/runtime.py
msprobe/core/common/utils.py
msprobe/core/compare/acc_compare.py
msprobe/core/compare/check.py
msprobe/core/compare/compare_cli.py
msprobe/core/compare/config.py
msprobe/core/compare/highlight.py
msprobe/core/compare/ms_to_pt_api.yaml
msprobe/core/compare/multiprocessing_compute.py
msprobe/core/compare/npy_compare.py
msprobe/core/compare/utils.py
msprobe/core/compare/diff_analyze/__init__.py
msprobe/core/compare/diff_analyze/diff_analyze_threshold.yaml
msprobe/core/compare/diff_analyze/first_diff_analyze.py
msprobe/core/compare/find_first/__init__.py
msprobe/core/compare/find_first/analyzer.py
msprobe/core/compare/find_first/data_processor.py
msprobe/core/compare/find_first/graph.py
msprobe/core/compare/find_first/utils.py
msprobe/core/compare/layer_mapping/__init__.py
msprobe/core/compare/layer_mapping/data_scope_parser.py
msprobe/core/compare/layer_mapping/layer_mapping.py
msprobe/core/compare/layer_mapping/postprocess_pass.py
msprobe/core/compare/merge_result/merge_result.py
msprobe/core/compare/merge_result/merge_result_cli.py
msprobe/core/compare/merge_result/utils.py
msprobe/core/config_check/__init__.py
msprobe/core/config_check/config_check_cli.py
msprobe/core/config_check/config_checker.py
mindstudio_probe-8.3.2.dist-info/LICENSE
mindstudio_probe-8.3.2.dist-info/METADATA
mindstudio_probe-8.3.2.dist-info/WHEEL
mindstudio_probe-8.3.2.dist-info/entry_points.txt
mindstudio_probe-8.3.2.dist-info/top_level.txt
mindstudio_probe-8.3.2.dist-info/RECORD
